{
  "2024-3-19": [
    [
      "2024-03-19 01:22PM",
      "Katz Center holds discussion on history of antisemitism in elite college admissions"
    ]
  ],
  "2024-3-20": [
    [
      "2024-03-20 04:14PM",
      "Katz Center holds discussion on history of antisemitism in elite college admissions"
    ]
  ],
  "2024-3-21": [
    [
      "2024-03-21 04:14PM",
      "Katz Center holds discussion on history of antisemitism in elite college admissions"
    ]
  ],
  "2024-3-22": [
    [
      "2024-03-22 04:13PM",
      "Katz Center holds discussion on history of antisemitism in elite college admissions"
    ]
  ],
  "2024-3-23": [
    [
      "2024-03-23 04:13PM",
      "Katz Center holds discussion on history of antisemitism in elite college admissions"
    ]
  ]
}